{"last_node_id":111,"last_link_id":4309,"nodes":[{"id":1,"type":"VAEEncode","pos":[1468,836],"size":{"0":210,"1":50},"flags":{},"order":40,"mode":0,"inputs":[{"name":"pixels","type":"IMAGE","link":4074,"label":"pixels"},{"name":"vae","type":"VAE","link":null,"label":"vae"}],"outputs":[{"name":"LATENT","type":"LATENT","links":[1506],"slot_index":0,"shape":3,"label":"LATENT"}],"properties":{"Node name for S&R":"VAEEncode"},"color":"#414548","bgcolor":"#2d3134"},{"id":2,"type":"ControlNetLoader","pos":[1716,1496],"size":{"0":287.1700134277344,"1":58},"flags":{},"order":10,"mode":2,"outputs":[{"name":"CONTROL_NET","type":"CONTROL_NET","links":[2930],"slot_index":0,"shape":3,"label":"CONTROL_NET"}],"properties":{"Node name for S&R":"ControlNetLoader"},"widgets_values":["control_v11p_sd15_scribble_fp16.safetensors"],"color":"#414548","bgcolor":"#2d3134"},{"id":3,"type":"CheckpointLoaderSimple","pos":[1456,2416],"size":{"0":216,"1":100},"flags":{},"order":2,"mode":2,"outputs":[{"name":"MODEL","type":"MODEL","links":[2654],"slot_index":0,"label":"MODEL"},{"name":"CLIP","type":"CLIP","links":[2926,2927],"slot_index":1,"label":"CLIP"},{"name":"VAE","type":"VAE","links":[4109],"slot_index":2,"label":"VAE"}],"properties":{"Node name for S&R":"CheckpointLoaderSimple"},"widgets_values":["epicrealism_pureEvolutionV5-inpainting.safetensors"],"color":"#414548","bgcolor":"#2d3134"},{"id":4,"type":"ControlNetLoader","pos":[1736,1948],"size":{"0":320,"1":60},"flags":{"collapsed":false},"order":0,"mode":2,"outputs":[{"name":"CONTROL_NET","type":"CONTROL_NET","links":[516],"slot_index":0,"shape":3,"label":"CONTROL_NET"}],"properties":{"Node name for S&R":"ControlNetLoader"},"widgets_values":["control_v11p_sd15_inpaint_fp16.safetensors"],"color":"#414548","bgcolor":"#2d3134"},{"id":5,"type":"ACN_AdvancedControlNetApply","pos":[2068,1936],"size":{"0":236.8000030517578,"1":286},"flags":{},"order":61,"mode":2,"inputs":[{"name":"positive","type":"CONDITIONING","link":2918,"slot_index":0,"label":"positive"},{"name":"negative","type":"CONDITIONING","link":2919,"slot_index":1,"label":"negative"},{"name":"control_net","type":"CONTROL_NET","link":516,"label":"control_net"},{"name":"image","type":"IMAGE","link":517,"slot_index":3,"label":"image"},{"name":"mask_optional","type":"MASK","link":null,"slot_index":4,"label":"mask_optional"},{"name":"timestep_kf","type":"TIMESTEP_KEYFRAME","link":1254,"slot_index":5,"label":"timestep_kf"},{"name":"latent_kf_override","type":"LATENT_KEYFRAME","link":null,"slot_index":6,"label":"latent_kf_override"},{"name":"weights_override","type":"CONTROL_NET_WEIGHTS","link":520,"slot_index":7,"label":"weights_override"},{"name":"model_optional","type":"MODEL","link":null,"label":"model_optional"},{"name":"vae_optional","type":"VAE","link":null,"label":"vae_optional"}],"outputs":[{"name":"positive","type":"CONDITIONING","links":[3682],"slot_index":0,"shape":3,"label":"positive"},{"name":"negative","type":"CONDITIONING","links":[3683],"slot_index":1,"shape":3,"label":"negative"},{"name":"model_opt","type":"MODEL","links":[3941],"slot_index":2,"shape":3,"label":"model_opt"}],"title":"Apply Advanced ControlNet","properties":{"Node name for S&R":"ACN_AdvancedControlNetApply"},"widgets_values":[1,0,1,""],"color":"#414548","bgcolor":"#2d3134"},{"id":6,"type":"InpaintPreprocessor","pos":[1884,2048],"size":{"0":168,"1":48},"flags":{"collapsed":false},"order":49,"mode":2,"inputs":[{"name":"image","type":"IMAGE","link":4115,"label":"image"},{"name":"mask","type":"MASK","link":3716,"label":"mask"}],"outputs":[{"name":"IMAGE","type":"IMAGE","links":[517],"slot_index":0,"shape":3,"label":"IMAGE"}],"properties":{"Node name for S&R":"InpaintPreprocessor"},"color":"#414548","bgcolor":"#2d3134"},{"id":7,"type":"ScaledSoftControlNetWeights","pos":[1928,2136],"size":{"0":270,"1":126},"flags":{"collapsed":true},"order":4,"mode":2,"inputs":[{"name":"cn_extras","type":"CN_WEIGHTS_EXTRAS","link":null,"label":"cn_extras"}],"outputs":[{"name":"CN_WEIGHTS","type":"CONTROL_NET_WEIGHTS","links":[520],"slot_index":0,"shape":3,"label":"CN_WEIGHTS"},{"name":"TK_SHORTCUT","type":"TIMESTEP_KEYFRAME","links":[1254],"slot_index":1,"shape":3,"label":"TK_SHORTCUT"}],"title":"Scaled Soft","properties":{"Node name for S&R":"ScaledSoftControlNetWeights"},"widgets_values":[0.82,false,1,""],"color":"#414548","bgcolor":"#2d3134"},{"id":8,"type":"ControlNetApplyAdvanced","pos":[2016,1496],"size":{"0":232,"1":168},"flags":{},"order":54,"mode":2,"inputs":[{"name":"positive","type":"CONDITIONING","link":2914,"slot_index":0,"label":"positive"},{"name":"negative","type":"CONDITIONING","link":2915,"label":"negative"},{"name":"control_net","type":"CONTROL_NET","link":2930,"slot_index":2,"label":"control_net"},{"name":"image","type":"IMAGE","link":3243,"label":"image"},{"name":"strength","type":"FLOAT","link":4097,"widget":{"name":"strength"},"label":"strength"}],"outputs":[{"name":"positive","type":"CONDITIONING","links":[1523],"slot_index":0,"shape":3,"label":"positive"},{"name":"negative","type":"CONDITIONING","links":[1524],"slot_index":1,"shape":3,"label":"negative"}],"properties":{"Node name for S&R":"ControlNetApplyAdvanced"},"widgets_values":[1,0,1],"color":"#414548","bgcolor":"#2d3134"},{"id":9,"type":"CLIPTextEncode","pos":[1464,648],"size":{"0":210,"1":54},"flags":{"collapsed":false},"order":41,"mode":0,"inputs":[{"name":"clip","type":"CLIP","link":null,"label":"clip"},{"name":"text","type":"STRING","link":4072,"widget":{"name":"text"},"label":"text"}],"outputs":[{"name":"CONDITIONING","type":"CONDITIONING","links":[2909],"slot_index":0,"shape":3,"label":"CONDITIONING"}],"title":"positive","properties":{"Node name for S&R":"CLIPTextEncode"},"widgets_values":[""],"color":"#414548","bgcolor":"#2d3134"},{"id":10,"type":"CLIPTextEncode","pos":[1468,744],"size":{"0":210,"1":54},"flags":{"collapsed":false},"order":42,"mode":0,"inputs":[{"name":"clip","type":"CLIP","link":null,"label":"clip"},{"name":"text","type":"STRING","link":4073,"widget":{"name":"text"},"label":"text"}],"outputs":[{"name":"CONDITIONING","type":"CONDITIONING","links":[2908],"slot_index":0,"shape":3,"label":"CONDITIONING"}],"title":"negative","properties":{"Node name for S&R":"CLIPTextEncode"},"widgets_values":[""],"color":"#414548","bgcolor":"#2d3134"},{"id":11,"type":"KSampler","pos":[1724,644],"size":{"0":212,"1":216},"flags":{},"order":55,"mode":0,"inputs":[{"name":"model","type":"MODEL","link":null,"label":"model"},{"name":"positive","type":"CONDITIONING","link":2909,"label":"positive"},{"name":"negative","type":"CONDITIONING","link":2908,"slot_index":2,"label":"negative"},{"name":"latent_image","type":"LATENT","link":1506,"label":"latent_image"},{"name":"steps","type":"INT","link":null,"widget":{"name":"steps"},"label":"steps"},{"name":"cfg","type":"FLOAT","link":null,"widget":{"name":"cfg"},"label":"cfg"},{"name":"sampler_name","type":"COMBO","link":null,"widget":{"name":"sampler_name"},"label":"sampler_name"},{"name":"denoise","type":"FLOAT","link":4075,"widget":{"name":"denoise"},"label":"denoise"},{"name":"scheduler","type":"COMBO","link":null,"widget":{"name":"scheduler"},"label":"scheduler"},{"name":"seed","type":"INT","link":4076,"widget":{"name":"seed"},"label":"seed"}],"outputs":[{"name":"LATENT","type":"LATENT","links":[2144],"slot_index":0,"label":"LATENT"}],"properties":{"Node name for S&R":"KSampler"},"widgets_values":[0,"fixed",6,1,"lcm","sgm_uniform",1],"color":"#232","bgcolor":"#353"},{"id":12,"type":"KSampler","pos":[2524,1504],"size":{"0":212,"1":220},"flags":{},"order":64,"mode":2,"inputs":[{"name":"model","type":"MODEL","link":null,"label":"model"},{"name":"positive","type":"CONDITIONING","link":1523,"label":"positive"},{"name":"negative","type":"CONDITIONING","link":1524,"slot_index":2,"label":"negative"},{"name":"latent_image","type":"LATENT","link":2913,"label":"latent_image"},{"name":"seed","type":"INT","link":4113,"widget":{"name":"seed"},"label":"seed"},{"name":"steps","type":"INT","link":null,"widget":{"name":"steps"},"label":"steps"},{"name":"cfg","type":"FLOAT","link":null,"widget":{"name":"cfg"},"label":"cfg"},{"name":"scheduler","type":"COMBO","link":null,"widget":{"name":"scheduler"},"label":"scheduler"},{"name":"sampler_name","type":"COMBO","link":null,"widget":{"name":"sampler_name"},"label":"sampler_name"}],"outputs":[{"name":"LATENT","type":"LATENT","links":[2148],"slot_index":0,"label":"LATENT"}],"properties":{"Node name for S&R":"KSampler"},"widgets_values":[0,"fixed",6,1,"lcm","sgm_uniform",1],"color":"#232","bgcolor":"#353"},{"id":13,"type":"KSampler","pos":[1928,2420],"size":{"0":210,"1":234},"flags":{},"order":60,"mode":2,"inputs":[{"name":"model","type":"MODEL","link":2655,"label":"model"},{"name":"positive","type":"CONDITIONING","link":2732,"label":"positive"},{"name":"negative","type":"CONDITIONING","link":2733,"slot_index":2,"label":"negative"},{"name":"latent_image","type":"LATENT","link":2736,"slot_index":3,"label":"latent_image"},{"name":"seed","type":"INT","link":4112,"widget":{"name":"seed"},"label":"seed"}],"outputs":[{"name":"LATENT","type":"LATENT","links":[2146],"slot_index":0,"label":"LATENT"}],"properties":{"Node name for S&R":"KSampler"},"widgets_values":[0,"fixed",24,3,"dpmpp_2m","karras",1],"color":"#232","bgcolor":"#353"},{"id":14,"type":"KSampler","pos":[2312,1936],"size":{"0":210,"1":218},"flags":{},"order":71,"mode":2,"inputs":[{"name":"model","type":"MODEL","link":3941,"label":"model"},{"name":"positive","type":"CONDITIONING","link":3682,"label":"positive"},{"name":"negative","type":"CONDITIONING","link":3683,"slot_index":2,"label":"negative"},{"name":"latent_image","type":"LATENT","link":3684,"label":"latent_image"},{"name":"seed","type":"INT","link":4117,"widget":{"name":"seed"},"label":"seed"},{"name":"steps","type":"INT","link":null,"widget":{"name":"steps"},"label":"steps"},{"name":"cfg","type":"FLOAT","link":null,"widget":{"name":"cfg"},"label":"cfg"},{"name":"scheduler","type":"COMBO","link":null,"widget":{"name":"scheduler"},"label":"scheduler"},{"name":"sampler_name","type":"COMBO","link":null,"widget":{"name":"sampler_name"},"label":"sampler_name"}],"outputs":[{"name":"LATENT","type":"LATENT","links":[2152],"slot_index":0,"label":"LATENT"}],"properties":{"Node name for S&R":"KSampler"},"widgets_values":[0,"fixed",6,1,"lcm","sgm_uniform",1],"color":"#232","bgcolor":"#353"},{"id":15,"type":"KSampler","pos":[2924,632],"size":{"0":210,"1":220},"flags":{},"order":50,"mode":2,"inputs":[{"name":"model","type":"MODEL","link":null,"label":"model"},{"name":"positive","type":"CONDITIONING","link":2923,"label":"positive"},{"name":"negative","type":"CONDITIONING","link":2922,"slot_index":2,"label":"negative"},{"name":"latent_image","type":"LATENT","link":2921,"label":"latent_image"},{"name":"seed","type":"INT","link":4129,"widget":{"name":"seed"},"label":"seed"},{"name":"steps","type":"INT","link":null,"widget":{"name":"steps"},"label":"steps"},{"name":"cfg","type":"FLOAT","link":null,"widget":{"name":"cfg"},"label":"cfg"},{"name":"scheduler","type":"COMBO","link":null,"widget":{"name":"scheduler"},"label":"scheduler"},{"name":"sampler_name","type":"COMBO","link":null,"widget":{"name":"sampler_name"},"label":"sampler_name"}],"outputs":[{"name":"LATENT","type":"LATENT","links":[2141],"slot_index":0,"label":"LATENT"}],"properties":{"Node name for S&R":"KSampler"},"widgets_values":[0,"fixed",6,1,"lcm","sgm_uniform",1],"color":"#232","bgcolor":"#353"},{"id":16,"type":"ControlNetLoader","pos":[1696,1076],"size":{"0":290,"1":60},"flags":{},"order":9,"mode":2,"outputs":[{"name":"CONTROL_NET","type":"CONTROL_NET","links":[1554],"slot_index":0,"shape":3,"label":"CONTROL_NET"}],"properties":{"Node name for S&R":"ControlNetLoader"},"widgets_values":["control_v11p_sd15_lineart_fp16.safetensors"],"color":"#414548","bgcolor":"#2d3134"},{"id":17,"type":"ControlNetApplyAdvanced","pos":[1996,1064],"size":{"0":240,"1":170},"flags":{},"order":52,"mode":2,"inputs":[{"name":"positive","type":"CONDITIONING","link":2910,"slot_index":0,"label":"positive"},{"name":"negative","type":"CONDITIONING","link":2911,"label":"negative"},{"name":"control_net","type":"CONTROL_NET","link":1554,"slot_index":2,"label":"control_net"},{"name":"image","type":"IMAGE","link":2196,"slot_index":3,"label":"image"}],"outputs":[{"name":"positive","type":"CONDITIONING","links":[1556],"slot_index":0,"shape":3,"label":"positive"},{"name":"negative","type":"CONDITIONING","links":[1557],"slot_index":1,"shape":3,"label":"negative"}],"properties":{"Node name for S&R":"ControlNetApplyAdvanced"},"widgets_values":[0.7,0,1],"color":"#414548","bgcolor":"#2d3134"},{"id":18,"type":"KSampler","pos":[2536,1072],"size":{"0":210,"1":220},"flags":{},"order":63,"mode":2,"inputs":[{"name":"model","type":"MODEL","link":null,"label":"model"},{"name":"positive","type":"CONDITIONING","link":1556,"label":"positive"},{"name":"negative","type":"CONDITIONING","link":1557,"slot_index":2,"label":"negative"},{"name":"latent_image","type":"LATENT","link":2912,"label":"latent_image"},{"name":"seed","type":"INT","link":4114,"widget":{"name":"seed"},"label":"seed"},{"name":"steps","type":"INT","link":null,"widget":{"name":"steps"},"label":"steps"},{"name":"cfg","type":"FLOAT","link":null,"widget":{"name":"cfg"},"label":"cfg"},{"name":"scheduler","type":"COMBO","link":null,"widget":{"name":"scheduler"},"label":"scheduler"},{"name":"sampler_name","type":"COMBO","link":null,"widget":{"name":"sampler_name"},"label":"sampler_name"},{"name":"denoise","type":"FLOAT","link":4091,"widget":{"name":"denoise"},"label":"denoise"}],"outputs":[{"name":"LATENT","type":"LATENT","links":[2150],"slot_index":0,"label":"LATENT"}],"properties":{"Node name for S&R":"KSampler"},"widgets_values":[0,"fixed",6,1,"lcm","sgm_uniform",1],"color":"#232","bgcolor":"#353"},{"id":19,"type":"VAEDecode","pos":[3144,632],"size":{"0":160,"1":50},"flags":{},"order":62,"mode":2,"inputs":[{"name":"samples","type":"LATENT","link":2141,"label":"samples"},{"name":"vae","type":"VAE","link":null,"label":"vae"}],"outputs":[{"name":"IMAGE","type":"IMAGE","links":[4140],"slot_index":0,"shape":3,"label":"IMAGE"}],"properties":{"Node name for S&R":"VAEDecode"},"color":"#414548","bgcolor":"#2d3134"},{"id":20,"type":"VAEDecode","pos":[1952,644],"size":{"0":160,"1":50},"flags":{},"order":65,"mode":0,"inputs":[{"name":"samples","type":"LATENT","link":2144,"label":"samples"},{"name":"vae","type":"VAE","link":null,"label":"vae"}],"outputs":[{"name":"IMAGE","type":"IMAGE","links":[4137],"slot_index":0,"shape":3,"label":"IMAGE"}],"properties":{"Node name for S&R":"VAEDecode"},"color":"#414548","bgcolor":"#2d3134"},{"id":21,"type":"VAEDecode","pos":[2152,2420],"size":{"0":160,"1":50},"flags":{},"order":70,"mode":2,"inputs":[{"name":"samples","type":"LATENT","link":2146,"label":"samples"},{"name":"vae","type":"VAE","link":null,"label":"vae"}],"outputs":[{"name":"IMAGE","type":"IMAGE","links":[4145],"slot_index":0,"shape":3,"label":"IMAGE"}],"properties":{"Node name for S&R":"VAEDecode"},"color":"#414548","bgcolor":"#2d3134"},{"id":22,"type":"VAEDecode","pos":[2752,1504],"size":{"0":150,"1":50},"flags":{},"order":74,"mode":2,"inputs":[{"name":"samples","type":"LATENT","link":2148,"label":"samples"},{"name":"vae","type":"VAE","link":null,"label":"vae"}],"outputs":[{"name":"IMAGE","type":"IMAGE","links":[4143],"slot_index":0,"shape":3,"label":"IMAGE"}],"properties":{"Node name for S&R":"VAEDecode"},"color":"#414548","bgcolor":"#2d3134"},{"id":23,"type":"VAEDecode","pos":[2760,1072],"size":{"0":160,"1":50},"flags":{},"order":73,"mode":2,"inputs":[{"name":"samples","type":"LATENT","link":2150,"label":"samples"},{"name":"vae","type":"VAE","link":null,"label":"vae"}],"outputs":[{"name":"IMAGE","type":"IMAGE","links":[4142],"slot_index":0,"shape":3,"label":"IMAGE"}],"properties":{"Node name for S&R":"VAEDecode"},"color":"#414548","bgcolor":"#2d3134"},{"id":24,"type":"VAEDecode","pos":[2532,1940],"size":{"0":140,"1":46},"flags":{},"order":81,"mode":2,"inputs":[{"name":"samples","type":"LATENT","link":2152,"label":"samples"},{"name":"vae","type":"VAE","link":null,"label":"vae"}],"outputs":[{"name":"IMAGE","type":"IMAGE","links":[4144],"slot_index":0,"shape":3,"label":"IMAGE"}],"properties":{"Node name for S&R":"VAEDecode"},"color":"#414548","bgcolor":"#2d3134"},{"id":25,"type":"AIO_Preprocessor","pos":[1696,1176],"size":{"0":290,"1":82},"flags":{},"order":32,"mode":2,"inputs":[{"name":"image","type":"IMAGE","link":4130,"slot_index":0,"label":"image"}],"outputs":[{"name":"IMAGE","type":"IMAGE","links":[2196,4131],"slot_index":0,"shape":3,"label":"IMAGE"}],"properties":{"Node name for S&R":"AIO_Preprocessor"},"widgets_values":["LineArtPreprocessor",512],"color":"#414548","bgcolor":"#2d3134"},{"id":26,"type":"CheckpointLoaderSimple","pos":[596,-260],"size":{"0":340,"1":100},"flags":{"pinned":false},"order":16,"mode":0,"outputs":[{"name":"MODEL","type":"MODEL","links":[4170],"slot_index":0,"shape":3,"label":"MODEL"},{"name":"CLIP","type":"CLIP","links":[4171],"slot_index":1,"shape":3,"label":"CLIP"},{"name":"VAE","type":"VAE","links":[2961],"slot_index":2,"shape":3,"label":"VAE"}],"properties":{"Node name for S&R":"CheckpointLoaderSimple"},"widgets_values":["epicrealism_naturalSinRC1VAE.safetensors"],"color":"#404440","bgcolor":"#2c302c"},{"id":27,"type":"Anything Everywhere?","pos":[1720,-348],"size":{"0":212,"1":128},"flags":{"collapsed":true},"order":104,"mode":2,"inputs":[{"name":"COMBO","type":"*","link":4267,"label":"COMBO"}],"title":"scheduler","properties":{"Node name for S&R":"Anything Everywhere?","group_restricted":false,"color_restricted":false},"widgets_values":[".*","scheduler",".*"],"color":"#364736","bgcolor":"#223322"},{"id":28,"type":"Anything Everywhere?","pos":[1720,-392],"size":{"0":212,"1":128},"flags":{"collapsed":true},"order":103,"mode":2,"inputs":[{"name":"COMBO","type":"*","link":4266,"label":"COMBO"}],"title":"sampler","properties":{"Node name for S&R":"Anything Everywhere?","group_restricted":false,"color_restricted":false},"widgets_values":[".*","sampler",".*"],"color":"#364736","bgcolor":"#223322"},{"id":29,"type":"Anything Everywhere?","pos":[1716,-432],"size":{"0":212,"1":128},"flags":{"collapsed":true},"order":102,"mode":2,"inputs":[{"name":"FLOAT","type":"*","link":4265,"label":"FLOAT","color_on":""}],"title":"cfg","properties":{"Node name for S&R":"Anything Everywhere?","group_restricted":false,"color_restricted":false},"widgets_values":[".*","cfg",".*"],"color":"#364736","bgcolor":"#223322"},{"id":30,"type":"Anything Everywhere?","pos":[1716,-472],"size":{"0":212,"1":128},"flags":{"collapsed":true},"order":101,"mode":2,"inputs":[{"name":"INT","type":"*","link":4262,"label":"INT","color_on":"#29699C"}],"title":"steps","properties":{"Node name for S&R":"Anything Everywhere?","group_restricted":false,"color_restricted":false},"widgets_values":[".*","steps",".*"],"color":"#364736","bgcolor":"#223322"},{"id":31,"type":"DifferentialDiffusion","pos":[1696,2420],"size":{"0":200,"1":30},"flags":{"collapsed":false},"order":21,"mode":2,"inputs":[{"name":"model","type":"MODEL","link":2654,"slot_index":0,"label":"model"}],"outputs":[{"name":"MODEL","type":"MODEL","links":[2655],"slot_index":0,"shape":3,"label":"MODEL"}],"properties":{"Node name for S&R":"DifferentialDiffusion"},"color":"#414548","bgcolor":"#2d3134"},{"id":32,"type":"InpaintModelConditioning","pos":[1696,2496],"size":{"0":201.60000610351562,"1":110},"flags":{},"order":46,"mode":2,"inputs":[{"name":"positive","type":"CONDITIONING","link":2916,"label":"positive"},{"name":"negative","type":"CONDITIONING","link":2917,"label":"negative"},{"name":"vae","type":"VAE","link":4109,"label":"vae"},{"name":"pixels","type":"IMAGE","link":4104,"label":"pixels"},{"name":"mask","type":"MASK","link":4105,"label":"mask"}],"outputs":[{"name":"positive","type":"CONDITIONING","links":[2732],"slot_index":0,"shape":3,"label":"positive"},{"name":"negative","type":"CONDITIONING","links":[2733],"slot_index":1,"shape":3,"label":"negative"},{"name":"latent","type":"LATENT","links":[2736],"slot_index":2,"shape":3,"label":"latent"}],"properties":{"Node name for S&R":"InpaintModelConditioning"},"color":"#414548","bgcolor":"#2d3134"},{"id":33,"type":"VAEEncode","pos":[1464,1252],"size":{"0":210,"1":50},"flags":{},"order":31,"mode":2,"inputs":[{"name":"pixels","type":"IMAGE","link":4090,"label":"pixels"},{"name":"vae","type":"VAE","link":null,"label":"vae"}],"outputs":[{"name":"LATENT","type":"LATENT","links":[2912],"slot_index":0,"shape":3,"label":"LATENT"}],"properties":{"Node name for S&R":"VAEEncode"},"color":"#414548","bgcolor":"#2d3134"},{"id":34,"type":"CLIPTextEncode","pos":[1464,1072],"size":{"0":210,"1":54},"flags":{"collapsed":false},"order":33,"mode":2,"inputs":[{"name":"clip","type":"CLIP","link":null,"label":"clip"},{"name":"text","type":"STRING","link":4088,"widget":{"name":"text"},"label":"text"}],"outputs":[{"name":"CONDITIONING","type":"CONDITIONING","links":[2910],"slot_index":0,"shape":3,"label":"CONDITIONING"}],"title":"positive","properties":{"Node name for S&R":"CLIPTextEncode"},"widgets_values":[""],"color":"#414548","bgcolor":"#2d3134"},{"id":35,"type":"CLIPTextEncode","pos":[1464,1160],"size":{"0":210,"1":54},"flags":{"collapsed":false},"order":34,"mode":2,"inputs":[{"name":"clip","type":"CLIP","link":null,"label":"clip"},{"name":"text","type":"STRING","link":4089,"widget":{"name":"text"},"label":"text"}],"outputs":[{"name":"CONDITIONING","type":"CONDITIONING","links":[2911],"slot_index":0,"shape":3,"label":"CONDITIONING"}],"title":"negative","properties":{"Node name for S&R":"CLIPTextEncode"},"widgets_values":[""],"color":"#414548","bgcolor":"#2d3134"},{"id":36,"type":"CLIPTextEncode","pos":[1480,1492],"size":{"0":210,"1":54},"flags":{"collapsed":false},"order":37,"mode":2,"inputs":[{"name":"clip","type":"CLIP","link":null,"label":"clip"},{"name":"text","type":"STRING","link":4094,"widget":{"name":"text"},"label":"text"}],"outputs":[{"name":"CONDITIONING","type":"CONDITIONING","links":[2914],"slot_index":0,"shape":3,"label":"CONDITIONING"}],"title":"positive","properties":{"Node name for S&R":"CLIPTextEncode"},"widgets_values":[""],"color":"#414548","bgcolor":"#2d3134"},{"id":37,"type":"CLIPTextEncode","pos":[1480,1580],"size":{"0":210,"1":54},"flags":{"collapsed":false},"order":38,"mode":2,"inputs":[{"name":"clip","type":"CLIP","link":null,"label":"clip"},{"name":"text","type":"STRING","link":4095,"widget":{"name":"text"},"label":"text"}],"outputs":[{"name":"CONDITIONING","type":"CONDITIONING","links":[2915],"slot_index":0,"shape":3,"label":"CONDITIONING"}],"title":"negative","properties":{"Node name for S&R":"CLIPTextEncode"},"widgets_values":[""],"color":"#414548","bgcolor":"#2d3134"},{"id":38,"type":"EmptyLatentImage","pos":[1480,1668],"size":{"0":210,"1":80},"flags":{"collapsed":false},"order":39,"mode":2,"inputs":[{"name":"width","type":"INT","link":4092,"slot_index":0,"widget":{"name":"width"},"label":"width"},{"name":"height","type":"INT","link":4093,"slot_index":1,"widget":{"name":"height"},"label":"height"}],"outputs":[{"name":"LATENT","type":"LATENT","links":[2913],"slot_index":0,"shape":3,"label":"LATENT"}],"properties":{"Node name for S&R":"EmptyLatentImage"},"widgets_values":[512,512,1],"color":"#414548","bgcolor":"#2d3134"},{"id":39,"type":"CLIPTextEncode","pos":[1456,2552],"size":{"0":212,"1":56},"flags":{"collapsed":false},"order":22,"mode":2,"inputs":[{"name":"clip","type":"CLIP","link":2927,"label":"clip"},{"name":"text","type":"STRING","link":4107,"widget":{"name":"text"},"label":"text"}],"outputs":[{"name":"CONDITIONING","type":"CONDITIONING","links":[2916],"slot_index":0,"shape":3,"label":"CONDITIONING"}],"title":"positive","properties":{"Node name for S&R":"CLIPTextEncode"},"widgets_values":[""],"color":"#414548","bgcolor":"#2d3134"},{"id":40,"type":"CLIPTextEncode","pos":[1456,2644],"size":{"0":212,"1":56},"flags":{"collapsed":false},"order":23,"mode":2,"inputs":[{"name":"clip","type":"CLIP","link":2926,"label":"clip"},{"name":"text","type":"STRING","link":4108,"widget":{"name":"text"},"label":"text"}],"outputs":[{"name":"CONDITIONING","type":"CONDITIONING","links":[2917],"slot_index":0,"shape":3,"label":"CONDITIONING"}],"title":"negative","properties":{"Node name for S&R":"CLIPTextEncode"},"widgets_values":[""],"color":"#414548","bgcolor":"#2d3134"},{"id":41,"type":"CLIPTextEncode","pos":[1476,1928],"size":{"0":230,"1":54},"flags":{"collapsed":false},"order":26,"mode":2,"inputs":[{"name":"clip","type":"CLIP","link":null,"label":"clip"},{"name":"text","type":"STRING","link":4110,"widget":{"name":"text"},"label":"text"}],"outputs":[{"name":"CONDITIONING","type":"CONDITIONING","links":[2918],"slot_index":0,"shape":3,"label":"CONDITIONING"}],"title":"positive","properties":{"Node name for S&R":"CLIPTextEncode"},"widgets_values":[""],"color":"#414548","bgcolor":"#2d3134"},{"id":42,"type":"CLIPTextEncode","pos":[1476,2016],"size":{"0":230,"1":54},"flags":{"collapsed":false},"order":27,"mode":2,"inputs":[{"name":"clip","type":"CLIP","link":null,"label":"clip"},{"name":"text","type":"STRING","link":4111,"widget":{"name":"text"},"label":"text"}],"outputs":[{"name":"CONDITIONING","type":"CONDITIONING","links":[2919],"slot_index":0,"shape":3,"label":"CONDITIONING"}],"title":"negative","properties":{"Node name for S&R":"CLIPTextEncode"},"widgets_values":[""],"color":"#414548","bgcolor":"#2d3134"},{"id":43,"type":"VAEEncodeForInpaint","pos":[1476,2108],"size":{"0":230,"1":100},"flags":{"collapsed":false},"order":48,"mode":2,"inputs":[{"name":"pixels","type":"IMAGE","link":4128,"slot_index":0,"label":"pixels"},{"name":"vae","type":"VAE","link":null,"slot_index":1,"label":"vae"},{"name":"mask","type":"MASK","link":3715,"label":"mask"}],"outputs":[{"name":"LATENT","type":"LATENT","links":[3684],"slot_index":0,"shape":3,"label":"LATENT"}],"properties":{"Node name for S&R":"VAEEncodeForInpaint"},"widgets_values":[25],"color":"#414548","bgcolor":"#2d3134"},{"id":44,"type":"CLIPTextEncode","pos":[2684,632],"size":{"0":210,"1":54},"flags":{"collapsed":false},"order":28,"mode":2,"inputs":[{"name":"clip","type":"CLIP","link":null,"label":"clip"},{"name":"text","type":"STRING","link":4123,"widget":{"name":"text"},"label":"text"}],"outputs":[{"name":"CONDITIONING","type":"CONDITIONING","links":[2923],"slot_index":0,"shape":3,"label":"CONDITIONING"}],"title":"positive","properties":{"Node name for S&R":"CLIPTextEncode"},"widgets_values":[""],"color":"#414548","bgcolor":"#2d3134"},{"id":45,"type":"CLIPTextEncode","pos":[2684,720],"size":{"0":210,"1":54},"flags":{"collapsed":false},"order":29,"mode":2,"inputs":[{"name":"clip","type":"CLIP","link":null,"label":"clip"},{"name":"text","type":"STRING","link":4124,"widget":{"name":"text"},"label":"text"}],"outputs":[{"name":"CONDITIONING","type":"CONDITIONING","links":[2922],"slot_index":0,"shape":3,"label":"CONDITIONING"}],"title":"negative","properties":{"Node name for S&R":"CLIPTextEncode"},"widgets_values":[""],"color":"#414548","bgcolor":"#2d3134"},{"id":46,"type":"EmptyLatentImage","pos":[2684,812],"size":{"0":210,"1":80},"flags":{"collapsed":false},"order":30,"mode":2,"inputs":[{"name":"width","type":"INT","link":4121,"slot_index":0,"widget":{"name":"width"},"label":"width"},{"name":"height","type":"INT","link":4122,"slot_index":1,"widget":{"name":"height"},"label":"height"}],"outputs":[{"name":"LATENT","type":"LATENT","links":[2921],"slot_index":0,"shape":3,"label":"LATENT"}],"properties":{"Node name for S&R":"EmptyLatentImage"},"widgets_values":[512,512,1],"color":"#414548","bgcolor":"#2d3134"},{"id":47,"type":"Fast Groups Muter (rgthree)","pos":{"0":64,"1":432,"2":0,"3":0,"4":0,"5":0,"6":0,"7":0,"8":0,"9":0},"size":{"0":408,"1":228},"flags":{},"order":18,"mode":0,"inputs":[],"outputs":[{"name":"OPT_CONNECTION","type":"*","links":null,"label":"OPT_CONNECTION"}],"title":"📁","properties":{"matchColors":"pale_blue","matchTitle":"","showNav":true,"sort":"alphanumeric","customSortAlphabet":"","toggleRestriction":"always one"},"color":"#2b4557","bgcolor":"#2b4557"},{"id":48,"type":"Fast Groups Muter (rgthree)","pos":{"0":68,"1":248,"2":0,"3":0,"4":0,"5":0,"6":0,"7":0,"8":0,"9":0},"size":{"0":404,"1":132},"flags":{"collapsed":false},"order":17,"mode":0,"inputs":[],"outputs":[{"name":"OPT_CONNECTION","type":"*","links":[],"label":"OPT_CONNECTION"}],"title":"⚙️","properties":{"matchColors":"green","matchTitle":"","showNav":true,"sort":"position","customSortAlphabet":"","toggleRestriction":"always one"},"color":"#4e5e4e","bgcolor":"#4e5e4e"},{"id":49,"type":"Anything Everywhere","pos":[916,-188],"size":{"0":232,"1":76},"flags":{"collapsed":true},"order":45,"mode":0,"inputs":[{"name":"VAE","type":"*","link":2961,"color_on":"#FF6E6E","label":"VAE"}],"title":"VAE","properties":{"Node name for S&R":"Anything Everywhere","group_restricted":false,"color_restricted":false},"widgets_values":[],"color":"#404440","bgcolor":"#2c302c"},{"id":50,"type":"LoraLoader","pos":[1208,-572],"size":{"0":296,"1":128},"flags":{},"order":76,"mode":2,"inputs":[{"name":"model","type":"MODEL","link":3143,"label":"model"},{"name":"clip","type":"CLIP","link":3144,"label":"clip"}],"outputs":[{"name":"MODEL","type":"MODEL","links":[4234],"slot_index":0,"shape":3,"label":"MODEL"},{"name":"CLIP","type":"CLIP","links":[4235],"slot_index":1,"shape":3,"label":"CLIP"}],"title":"Detail LoRA","properties":{"Node name for S&R":"LoraLoader"},"widgets_values":["add_detail.safetensors",1,1],"color":"#404440","bgcolor":"#2c302c"},{"id":51,"type":"LoraLoader","pos":[1208,-404],"size":{"0":296,"1":126},"flags":{},"order":66,"mode":2,"inputs":[{"name":"model","type":"MODEL","link":4163,"label":"model"},{"name":"clip","type":"CLIP","link":4164,"label":"clip"}],"outputs":[{"name":"MODEL","type":"MODEL","links":[3143],"slot_index":0,"shape":3,"label":"MODEL"},{"name":"CLIP","type":"CLIP","links":[3144],"slot_index":1,"shape":3,"label":"CLIP"}],"title":"LCM LoRA","properties":{"Node name for S&R":"LoraLoader"},"widgets_values":["lcm\\SD1.5\\pytorch_lora_weights.safetensors",1,1],"color":"#404440","bgcolor":"#2c302c"},{"id":52,"type":"ImageUpscaleWithModel","pos":[3880,636],"size":{"0":272,"1":46},"flags":{},"order":24,"mode":2,"inputs":[{"name":"upscale_model","type":"UPSCALE_MODEL","link":3177,"slot_index":0,"label":"upscale_model"},{"name":"image","type":"IMAGE","link":4126,"label":"image"}],"outputs":[{"name":"IMAGE","type":"IMAGE","links":[4141],"slot_index":0,"shape":3,"label":"IMAGE"}],"properties":{"Node name for S&R":"ImageUpscaleWithModel"},"color":"#414548","bgcolor":"#2d3134"},{"id":53,"type":"UpscaleModelLoader","pos":[3880,728],"size":{"0":268,"1":58},"flags":{},"order":1,"mode":2,"outputs":[{"name":"UPSCALE_MODEL","type":"UPSCALE_MODEL","links":[3177],"shape":3,"label":"UPSCALE_MODEL"}],"properties":{"Node name for S&R":"UpscaleModelLoader"},"widgets_values":["4x-UltraSharp.pth"],"color":"#414548","bgcolor":"#2d3134"},{"id":54,"type":"AIO_Preprocessor","pos":[1716,1592],"size":{"0":288,"1":84},"flags":{"collapsed":false},"order":35,"mode":2,"inputs":[{"name":"image","type":"IMAGE","link":4099,"slot_index":0,"label":"image"}],"outputs":[{"name":"IMAGE","type":"IMAGE","links":[3243,4100],"slot_index":0,"shape":3,"label":"IMAGE"}],"properties":{"Node name for S&R":"AIO_Preprocessor"},"widgets_values":["Scribble_XDoG_Preprocessor",512],"color":"#414548","bgcolor":"#2d3134"},{"id":55,"type":"GrowMask","pos":[1480,2244],"size":{"0":315,"1":82},"flags":{"collapsed":true},"order":25,"mode":2,"inputs":[{"name":"mask","type":"MASK","link":4116,"label":"mask"}],"outputs":[{"name":"MASK","type":"MASK","links":[3715,3716],"slot_index":0,"shape":3,"label":"MASK"}],"properties":{"Node name for S&R":"GrowMask"},"widgets_values":[5,true],"color":"#414548","bgcolor":"#2d3134"},{"id":56,"type":"Note Plus (mtb)","pos":{"0":-912,"1":152,"2":0,"3":0,"4":0,"5":0,"6":0,"7":0,"8":0,"9":0},"size":{"0":560,"1":356},"flags":{},"order":19,"mode":2,"inputs":[],"outputs":[],"properties":{},"widgets_values":["\n<div class=\"hoverContainer\">\n\n        <div class=\"header\">\n          <span class=\"header_discrip\">How to install Requierments</span>\n\n        </div>\n    <div style=\"border-radius:16px;position: relative; width: 100%; overflow: hidden; padding-top: 48%;\">\n    \n    \n    \n<iframe title=\"YouTube video player\" src=\"https://www.youtube.com/embed/i__ciRbs3VA?si=KyetBmqHKJm_kAKH\"></iframe>\n    </div>\n</div>","markdown","body { height: 50px; width: 50px; }\r\n* { font-family: arial; }\r\ndiv { height: 100%; }\r\n.hoverContainer { height: 320px; width: 520px; }\r\niframe { position: absolute; top: 0; left: 0; right: 0; height: 100%; border: none; }\r\n.hoverContainer {\r\n    background: black;\r\n    border-radius: 28px;\r\n    padding: 18px;\r\n    display: flex;\r\n    flex-direction: column;\r\n    position: relative;\r\n    margin-bottom: 12px;\r\n    left: 50%;\r\n    top: 50%;\r\n    transform: translate(-50%, -50%);\r\n}\r\n.header_discrip { font-size: 21px; font-weight: 300; color: #6f6f6f; width: fit-content; }\r\n.header {\r\n    padding-bottom: 12px;\r\n    width: 100%;\r\n    height: 36px;\r\n    display: flex;\r\n    align-items: center;\r\n    justify-content: space-between;\r\n    flex-direction: row;\r\n}\r\n","one_dark"],"color":"#3a3a3a","bgcolor":"#262626","shape":1},{"id":57,"type":"🔹Photoshop ComfyUI Plugin","pos":[1192,632],"size":{"0":256,"1":256},"flags":{"collapsed":false},"order":14,"mode":0,"outputs":[{"name":"Canvas","type":"IMAGE","links":[4074],"slot_index":0,"shape":3,"label":"Canvas"},{"name":"Mask","type":"MASK","links":[],"slot_index":1,"shape":3,"label":"Mask"},{"name":"Slider","type":"FLOAT","links":[4075],"slot_index":2,"shape":3,"label":"Slider"},{"name":"Seed","type":"INT","links":[4076],"slot_index":3,"shape":3,"label":"Seed"},{"name":"+","type":"STRING","links":[4072],"slot_index":4,"shape":3,"label":"+"},{"name":"-","type":"STRING","links":[4073],"slot_index":5,"shape":3,"label":"-"},{"name":"W","type":"INT","links":[],"slot_index":6,"shape":3,"label":"W"},{"name":"H","type":"INT","links":[],"slot_index":7,"shape":3,"label":"H"}],"properties":{"Disable Preview":false,"Dont Hide Buttons":false,"Node name for S&R":"🔹Photoshop ComfyUI Plugin"},"color":"#414548","bgcolor":"#2d3134"},{"id":58,"type":"🔹Photoshop ComfyUI Plugin","pos":[1188,1060],"size":[252,256],"flags":{"collapsed":false},"order":8,"mode":2,"outputs":[{"name":"Canvas","type":"IMAGE","links":[4090,4130],"slot_index":0,"shape":3,"label":"Canvas"},{"name":"Mask","type":"MASK","links":[],"slot_index":1,"shape":3,"label":"Mask"},{"name":"Slider","type":"FLOAT","links":[4091],"slot_index":2,"shape":3,"label":"Slider"},{"name":"Seed","type":"INT","links":[4114],"slot_index":3,"shape":3,"label":"Seed"},{"name":"+","type":"STRING","links":[4088],"slot_index":4,"shape":3,"label":"+"},{"name":"-","type":"STRING","links":[4089],"slot_index":5,"shape":3,"label":"-"},{"name":"W","type":"INT","links":[],"slot_index":6,"shape":3,"label":"W"},{"name":"H","type":"INT","links":[],"slot_index":7,"shape":3,"label":"H"}],"properties":{"Disable Preview":false,"Dont Hide Buttons":false,"Node name for S&R":"🔹Photoshop ComfyUI Plugin"},"widgets_values":[],"color":"#414548","bgcolor":"#2d3134"},{"id":59,"type":"🔹Photoshop ComfyUI Plugin","pos":[1192,1492],"size":{"0":252,"1":256},"flags":{"collapsed":false},"order":13,"mode":2,"outputs":[{"name":"Canvas","type":"IMAGE","links":[4099],"slot_index":0,"shape":3,"label":"Canvas"},{"name":"Mask","type":"MASK","links":[],"slot_index":1,"shape":3,"label":"Mask"},{"name":"Slider","type":"FLOAT","links":[4098],"slot_index":2,"shape":3,"label":"Slider"},{"name":"Seed","type":"INT","links":[4113],"slot_index":3,"shape":3,"label":"Seed"},{"name":"+","type":"STRING","links":[4094],"slot_index":4,"shape":3,"label":"+"},{"name":"-","type":"STRING","links":[4095],"slot_index":5,"shape":3,"label":"-"},{"name":"W","type":"INT","links":[4092],"slot_index":6,"shape":3,"label":"W"},{"name":"H","type":"INT","links":[4093],"slot_index":7,"shape":3,"label":"H"}],"properties":{"Disable Preview":false,"Dont Hide Buttons":false,"Node name for S&R":"🔹Photoshop ComfyUI Plugin"},"color":"#414548","bgcolor":"#2d3134"},{"id":60,"type":"SimpleMath+","pos":[1860,1716],"size":{"0":212,"1":80},"flags":{"collapsed":true},"order":36,"mode":2,"inputs":[{"name":"a","type":"INT,FLOAT","link":4098,"slot_index":0,"label":"a"},{"name":"b","type":"INT,FLOAT","link":null,"label":"b"}],"outputs":[{"name":"INT","type":"INT","links":null,"shape":3,"label":"INT"},{"name":"FLOAT","type":"FLOAT","links":[4097],"slot_index":1,"shape":3,"label":"FLOAT"}],"properties":{"Node name for S&R":"SimpleMath+"},"widgets_values":["1 - a"]},{"id":61,"type":"PreviewImage","pos":[2264,1500],"size":{"0":244,"1":252},"flags":{},"order":53,"mode":2,"inputs":[{"name":"images","type":"IMAGE","link":4100,"label":"images"}],"properties":{"Node name for S&R":"PreviewImage"}},{"id":62,"type":"🔹Photoshop ComfyUI Plugin","pos":[1188,2416],"size":{"0":252,"1":256},"flags":{"collapsed":false},"order":3,"mode":2,"outputs":[{"name":"Canvas","type":"IMAGE","links":[4104],"slot_index":0,"shape":3,"label":"Canvas"},{"name":"Mask","type":"MASK","links":[4105],"slot_index":1,"shape":3,"label":"Mask"},{"name":"Slider","type":"FLOAT","links":[],"slot_index":2,"shape":3,"label":"Slider"},{"name":"Seed","type":"INT","links":[4112],"slot_index":3,"shape":3,"label":"Seed"},{"name":"+","type":"STRING","links":[4107],"slot_index":4,"shape":3,"label":"+"},{"name":"-","type":"STRING","links":[4108],"slot_index":5,"shape":3,"label":"-"},{"name":"W","type":"INT","links":[],"slot_index":6,"shape":3,"label":"W"},{"name":"H","type":"INT","links":[],"slot_index":7,"shape":3,"label":"H"}],"properties":{"Disable Preview":false,"Dont Hide Buttons":false,"Node name for S&R":"🔹Photoshop ComfyUI Plugin"},"color":"#414548","bgcolor":"#2d3134"},{"id":63,"type":"🔹Photoshop ComfyUI Plugin","pos":[1192,1936],"size":{"0":252,"1":256},"flags":{"collapsed":false},"order":6,"mode":2,"outputs":[{"name":"Canvas","type":"IMAGE","links":[4115,4128],"slot_index":0,"shape":3,"label":"Canvas"},{"name":"Mask","type":"MASK","links":[4116],"slot_index":1,"shape":3,"label":"Mask"},{"name":"Slider","type":"FLOAT","links":[],"slot_index":2,"shape":3,"label":"Slider"},{"name":"Seed","type":"INT","links":[4117],"slot_index":3,"shape":3,"label":"Seed"},{"name":"+","type":"STRING","links":[4110],"slot_index":4,"shape":3,"label":"+"},{"name":"-","type":"STRING","links":[4111],"slot_index":5,"shape":3,"label":"-"},{"name":"W","type":"INT","links":[],"slot_index":6,"shape":3,"label":"W"},{"name":"H","type":"INT","links":[],"slot_index":7,"shape":3,"label":"H"}],"properties":{"Disable Preview":false,"Dont Hide Buttons":false,"Node name for S&R":"🔹Photoshop ComfyUI Plugin"},"color":"#414548","bgcolor":"#2d3134"},{"id":64,"type":"🔹Photoshop ComfyUI Plugin","pos":[2412,632],"size":{"0":252,"1":256},"flags":{"collapsed":false},"order":7,"mode":2,"outputs":[{"name":"Canvas","type":"IMAGE","links":[],"slot_index":0,"shape":3,"label":"Canvas"},{"name":"Mask","type":"MASK","links":[],"slot_index":1,"shape":3,"label":"Mask"},{"name":"Slider","type":"FLOAT","links":[],"slot_index":2,"shape":3,"label":"Slider"},{"name":"Seed","type":"INT","links":[4129],"slot_index":3,"shape":3,"label":"Seed"},{"name":"+","type":"STRING","links":[4123],"slot_index":4,"shape":3,"label":"+"},{"name":"-","type":"STRING","links":[4124],"slot_index":5,"shape":3,"label":"-"},{"name":"W","type":"INT","links":[4121],"slot_index":6,"shape":3,"label":"W"},{"name":"H","type":"INT","links":[4122],"slot_index":7,"shape":3,"label":"H"}],"properties":{"Disable Preview":false,"Dont Hide Buttons":false,"Node name for S&R":"🔹Photoshop ComfyUI Plugin"},"color":"#414548","bgcolor":"#2d3134"},{"id":65,"type":"🔹Photoshop ComfyUI Plugin","pos":[3608,632],"size":{"0":252,"1":256},"flags":{"collapsed":false},"order":5,"mode":2,"outputs":[{"name":"Canvas","type":"IMAGE","links":[4126],"slot_index":0,"shape":3,"label":"Canvas"},{"name":"Mask","type":"MASK","links":[],"slot_index":1,"shape":3,"label":"Mask"},{"name":"Slider","type":"FLOAT","links":[],"slot_index":2,"shape":3,"label":"Slider"},{"name":"Seed","type":"INT","links":[],"slot_index":3,"shape":3,"label":"Seed"},{"name":"+","type":"STRING","links":[],"slot_index":4,"shape":3,"label":"+"},{"name":"-","type":"STRING","links":[],"slot_index":5,"shape":3,"label":"-"},{"name":"W","type":"INT","links":[],"slot_index":6,"shape":3,"label":"W"},{"name":"H","type":"INT","links":[],"slot_index":7,"shape":3,"label":"H"}],"properties":{"Disable Preview":false,"Dont Hide Buttons":false,"Node name for S&R":"🔹Photoshop ComfyUI Plugin"},"color":"#414548","bgcolor":"#2d3134"},{"id":66,"type":"PreviewImage","pos":[2256,1068],"size":{"0":244,"1":252},"flags":{},"order":51,"mode":2,"inputs":[{"name":"images","type":"IMAGE","link":4131,"label":"images"}],"properties":{"Node name for S&R":"PreviewImage"}},{"id":67,"type":"Label (rgthree)","pos":{"0":1188,"1":-856,"2":0,"3":0,"4":0,"5":0,"6":0,"7":0,"8":0,"9":0},"size":{"0":164.765625,"1":120},"flags":{"allow_interaction":true},"order":11,"mode":0,"inputs":[],"outputs":[],"title":"⚙️","properties":{"fontSize":120,"fontFamily":"Arial","fontColor":"#ffffff","textAlign":"left","backgroundColor":"transparent","padding":0,"borderRadius":0},"color":"#fff0","bgcolor":"#fff0"},{"id":68,"type":"Label (rgthree)","pos":{"0":32,"1":72,"2":0,"3":0,"4":0,"5":0,"6":0,"7":0,"8":0,"9":0},"size":{"0":431.66015625,"1":120},"flags":{"allow_interaction":true},"order":12,"mode":0,"inputs":[],"outputs":[],"title":"🔹1.9.3","properties":{"fontSize":120,"fontFamily":"Arial","fontColor":"#4a4a4a","textAlign":"left","backgroundColor":"transparent","padding":0,"borderRadius":0},"color":"#fff0","bgcolor":"#fff0"},{"id":69,"type":"Label (rgthree)","pos":{"0":1180,"1":368,"2":0,"3":0,"4":0,"5":0,"6":0,"7":0,"8":0,"9":0},"size":{"0":164.765625,"1":120},"flags":{"allow_interaction":true},"order":15,"mode":0,"inputs":[],"outputs":[],"title":"📁","properties":{"fontSize":120,"fontFamily":"Arial","fontColor":"#4a4a4a","textAlign":"left","backgroundColor":"transparent","padding":0,"borderRadius":0},"color":"#fff0","bgcolor":"#fff0"},{"id":70,"type":"🔹SendTo Photoshop Plugin","pos":[2128,640],"size":{"0":216,"1":248},"flags":{},"order":75,"mode":0,"inputs":[{"name":"output","type":"IMAGE","link":4137,"label":"output"}],"properties":{"Node name for S&R":"🔹SendTo Photoshop Plugin"},"color":"#414548","bgcolor":"#2d3134"},{"id":71,"type":"🔹SendTo Photoshop Plugin","pos":[3316,636],"size":{"0":216,"1":248},"flags":{},"order":72,"mode":2,"inputs":[{"name":"output","type":"IMAGE","link":4140,"label":"output"}],"properties":{"Node name for S&R":"🔹SendTo Photoshop Plugin"},"color":"#414548","bgcolor":"#2d3134"},{"id":72,"type":"🔹SendTo Photoshop Plugin","pos":[4168,640],"size":{"0":216,"1":248},"flags":{},"order":47,"mode":2,"inputs":[{"name":"output","type":"IMAGE","link":4141,"label":"output"}],"properties":{"Node name for S&R":"🔹SendTo Photoshop Plugin"},"color":"#414548","bgcolor":"#2d3134"},{"id":73,"type":"🔹SendTo Photoshop Plugin","pos":[2928,1072],"size":{"0":216,"1":248},"flags":{},"order":82,"mode":2,"inputs":[{"name":"output","type":"IMAGE","link":4142,"label":"output"}],"properties":{"Node name for S&R":"🔹SendTo Photoshop Plugin"},"color":"#414548","bgcolor":"#2d3134"},{"id":74,"type":"🔹SendTo Photoshop Plugin","pos":[2920,1504],"size":{"0":216,"1":248},"flags":{},"order":83,"mode":2,"inputs":[{"name":"output","type":"IMAGE","link":4143,"label":"output"}],"properties":{"Node name for S&R":"🔹SendTo Photoshop Plugin"},"color":"#414548","bgcolor":"#2d3134"},{"id":75,"type":"🔹SendTo Photoshop Plugin","pos":[2688,1944],"size":{"0":216,"1":248},"flags":{},"order":98,"mode":2,"inputs":[{"name":"output","type":"IMAGE","link":4144,"label":"output"}],"properties":{"Node name for S&R":"🔹SendTo Photoshop Plugin"},"color":"#414548","bgcolor":"#2d3134"},{"id":76,"type":"🔹SendTo Photoshop Plugin","pos":[2328,2424],"size":{"0":216,"1":248},"flags":{},"order":80,"mode":2,"inputs":[{"name":"output","type":"IMAGE","link":4145,"label":"output"}],"properties":{"Node name for S&R":"🔹SendTo Photoshop Plugin"},"color":"#414548","bgcolor":"#2d3134"},{"id":77,"type":"Reroute (rgthree)","pos":{"0":1060,"1":-404,"2":0,"3":0,"4":0,"5":0,"6":0,"7":0,"8":0,"9":0},"size":[40,30],"flags":{},"order":56,"mode":0,"inputs":[{"name":"","type":"*","link":4169,"dir":2,"has_old_label":true,"label":""}],"outputs":[{"name":"MODEL","type":"MODEL","links":[4163,4238],"slot_index":0,"dir":4,"has_old_label":true,"label":" "}],"properties":{"resizable":false,"size":[40,30],"connections_layout":["Bottom","Right"]}},{"id":78,"type":"Reroute (rgthree)","pos":{"0":1116,"1":-384,"2":0,"3":0,"4":0,"5":0,"6":0,"7":0,"8":0,"9":0},"size":[40,30],"flags":{},"order":58,"mode":0,"inputs":[{"name":"","type":"*","link":4173,"slot_index":0,"dir":2,"has_old_label":true,"label":""}],"outputs":[{"name":"CLIP","type":"CLIP","links":[4164,4239],"slot_index":0,"dir":4,"has_old_label":true,"label":" "}],"properties":{"resizable":false,"size":[40,30],"connections_layout":["Bottom","Right"]}},{"id":79,"type":"Reroute (rgthree)","pos":{"0":972,"1":-260,"2":0,"3":0,"4":0,"5":0,"6":0,"7":0,"8":0,"9":0},"size":[40,30],"flags":{},"order":43,"mode":0,"inputs":[{"name":"","type":"*","link":4170,"dir":3,"has_old_label":true,"label":" "}],"outputs":[{"name":"MODEL","type":"MODEL","links":[4169,4253],"slot_index":0,"dir":4,"has_old_label":true,"label":" "}],"properties":{"resizable":false,"size":[40,30]}},{"id":80,"type":"Reroute (rgthree)","pos":{"0":1024,"1":-240,"2":0,"3":0,"4":0,"5":0,"6":0,"7":0,"8":0,"9":0},"size":[40,30],"flags":{},"order":44,"mode":0,"inputs":[{"name":"","type":"*","link":4171,"dir":3,"has_old_label":true,"label":" "}],"outputs":[{"name":"CLIP","type":"CLIP","links":[4173,4178],"slot_index":0,"dir":4,"has_old_label":true,"label":" "}],"properties":{"resizable":false,"size":[40,30]}},{"id":81,"type":"Reroute (rgthree)","pos":{"0":1112,"1":-84,"2":0,"3":0,"4":0,"5":0,"6":0,"7":0,"8":0,"9":0},"size":[40,30],"flags":{},"order":59,"mode":0,"inputs":[{"name":"","type":"*","link":4178,"slot_index":0,"dir":1,"has_old_label":true,"label":""}],"outputs":[{"name":"CLIP","type":"CLIP","links":[4255,4257],"slot_index":0,"dir":4,"has_old_label":true,"label":" "}],"properties":{"resizable":false,"size":[40,30],"connections_layout":["Top","Right"]}},{"id":82,"type":"Reroute (rgthree)","pos":{"0":1056,"1":-104,"2":0,"3":0,"4":0,"5":0,"6":0,"7":0,"8":0,"9":0},"size":[40,30],"flags":{},"order":57,"mode":0,"inputs":[{"name":"","type":"*","link":4253,"slot_index":0,"dir":1,"has_old_label":true,"label":""}],"outputs":[{"name":"MODEL","type":"MODEL","links":[4254,4256],"slot_index":0,"dir":4,"has_old_label":true,"label":" "}],"properties":{"resizable":false,"size":[40,30],"connections_layout":["Top","Right"]}},{"id":83,"type":"Anything Everywhere","pos":[1716,-552],"size":{"0":212,"1":76},"flags":{"collapsed":true},"order":99,"mode":2,"inputs":[{"name":"MODEL","type":"*","link":4264,"color_on":"#B39DDB","label":"MODEL"}],"title":"model","properties":{"Node name for S&R":"Anything Everywhere","group_restricted":0,"color_restricted":0},"widgets_values":[],"color":"#364736","bgcolor":"#223322"},{"id":84,"type":"Anything Everywhere","pos":[1716,-512],"size":{"0":212,"1":76},"flags":{"collapsed":true},"order":100,"mode":2,"inputs":[{"name":"CLIP","type":"*","link":4263,"color_on":"#FFD500","label":"CLIP"}],"title":"clip","properties":{"Node name for S&R":"Anything Everywhere","group_restricted":0,"color_restricted":0},"widgets_values":[],"color":"#364736","bgcolor":"#223322"},{"id":85,"type":"workflow/Ksampler Config","pos":[1528,-572],"size":{"0":212,"1":232},"flags":{},"order":84,"mode":2,"inputs":[{"name":"model","type":"MODEL","link":4234,"label":"model"},{"name":"clip","type":"CLIP","link":4235,"label":"clip"}],"outputs":[{"name":"MODEL","type":"MODEL","links":[4264],"slot_index":0,"shape":3,"label":"MODEL"},{"name":"CLIP","type":"CLIP","links":[4263],"slot_index":1,"shape":3,"label":"CLIP"},{"name":"STEPS","type":"INT","links":[4262],"slot_index":2,"shape":3,"label":"STEPS"},{"name":"CFG","type":"FLOAT","links":[4265],"slot_index":3,"shape":3,"label":"CFG"},{"name":"SAMPLER","type":"COMBO","links":[4266],"slot_index":4,"shape":3,"label":"SAMPLER"},{"name":"SCHEDULER","type":"COMBO","links":[4267],"slot_index":5,"shape":3,"label":"SCHEDULER"}],"properties":{"Node name for S&R":"workflow/Ksampler Config"},"widgets_values":[4,24,3,"lcm","sgm_uniform"],"color":"#232","bgcolor":"#353"},{"id":86,"type":"Anything Everywhere?","pos":[2412,-348],"size":{"0":212,"1":128},"flags":{"collapsed":true},"order":110,"mode":0,"inputs":[{"name":"COMBO","type":"*","link":4271,"label":"COMBO"}],"title":"scheduler","properties":{"Node name for S&R":"Anything Everywhere?","group_restricted":false,"color_restricted":false},"widgets_values":[".*","scheduler",".*"],"color":"#364736","bgcolor":"#223322"},{"id":87,"type":"Anything Everywhere?","pos":[2412,-392],"size":{"0":212,"1":128},"flags":{"collapsed":true},"order":109,"mode":0,"inputs":[{"name":"COMBO","type":"*","link":4270,"label":"COMBO"}],"title":"sampler","properties":{"Node name for S&R":"Anything Everywhere?","group_restricted":false,"color_restricted":false},"widgets_values":[".*","sampler",".*"],"color":"#364736","bgcolor":"#223322"},{"id":88,"type":"Anything Everywhere?","pos":[2408,-432],"size":{"0":212,"1":128},"flags":{"collapsed":true},"order":108,"mode":0,"inputs":[{"name":"FLOAT","type":"*","link":4269,"label":"FLOAT","color_on":""}],"title":"cfg","properties":{"Node name for S&R":"Anything Everywhere?","group_restricted":false,"color_restricted":false},"widgets_values":[".*","cfg",".*"],"color":"#364736","bgcolor":"#223322"},{"id":89,"type":"Anything Everywhere?","pos":[2408,-472],"size":{"0":212,"1":128},"flags":{"collapsed":true},"order":107,"mode":0,"inputs":[{"name":"INT","type":"*","link":4268,"label":"INT","color_on":"#29699C"}],"title":"steps","properties":{"Node name for S&R":"Anything Everywhere?","group_restricted":false,"color_restricted":false},"widgets_values":[".*","steps",".*"],"color":"#364736","bgcolor":"#223322"},{"id":90,"type":"LoraLoader","pos":[1900,-572],"size":{"0":296,"1":128},"flags":{},"order":77,"mode":0,"inputs":[{"name":"model","type":"MODEL","link":4236,"label":"model"},{"name":"clip","type":"CLIP","link":4237,"label":"clip"}],"outputs":[{"name":"MODEL","type":"MODEL","links":[4242],"slot_index":0,"shape":3,"label":"MODEL"},{"name":"CLIP","type":"CLIP","links":[4243],"slot_index":1,"shape":3,"label":"CLIP"}],"title":"Detail LoRA","properties":{"Node name for S&R":"LoraLoader"},"widgets_values":["add_detail.safetensors",1,1],"color":"#404440","bgcolor":"#2c302c"},{"id":91,"type":"LoraLoader","pos":[1900,-404],"size":{"0":296,"1":126},"flags":{},"order":67,"mode":0,"inputs":[{"name":"model","type":"MODEL","link":4238,"label":"model"},{"name":"clip","type":"CLIP","link":4239,"label":"clip"}],"outputs":[{"name":"MODEL","type":"MODEL","links":[4236],"slot_index":0,"shape":3,"label":"MODEL"},{"name":"CLIP","type":"CLIP","links":[4237],"slot_index":1,"shape":3,"label":"CLIP"}],"title":"LCM LoRA","properties":{"Node name for S&R":"LoraLoader"},"widgets_values":["lcm\\SD1.5\\pytorch_lora_weights.safetensors",1,1],"color":"#404440","bgcolor":"#2c302c"},{"id":92,"type":"Anything Everywhere","pos":[2408,-552],"size":{"0":212,"1":76},"flags":{"collapsed":true},"order":105,"mode":0,"inputs":[{"name":"MODEL","type":"*","link":4240,"color_on":"#B39DDB","label":"MODEL"}],"title":"model","properties":{"Node name for S&R":"Anything Everywhere","group_restricted":0,"color_restricted":0},"widgets_values":[],"color":"#364736","bgcolor":"#223322"},{"id":93,"type":"Anything Everywhere","pos":[2408,-512],"size":{"0":212,"1":76},"flags":{"collapsed":true},"order":106,"mode":0,"inputs":[{"name":"CLIP","type":"*","link":4241,"color_on":"#FFD500","label":"CLIP"}],"title":"clip","properties":{"Node name for S&R":"Anything Everywhere","group_restricted":0,"color_restricted":0},"widgets_values":[],"color":"#364736","bgcolor":"#223322"},{"id":94,"type":"workflow/Ksampler Config","pos":[2220,-572],"size":{"0":212,"1":232},"flags":{},"order":85,"mode":0,"inputs":[{"name":"model","type":"MODEL","link":4242,"label":"model"},{"name":"clip","type":"CLIP","link":4243,"label":"clip"}],"outputs":[{"name":"MODEL","type":"MODEL","links":[4240],"shape":3,"label":"MODEL"},{"name":"CLIP","type":"CLIP","links":[4241],"shape":3,"label":"CLIP"},{"name":"STEPS","type":"INT","links":[4268],"slot_index":2,"shape":3,"label":"STEPS"},{"name":"CFG","type":"FLOAT","links":[4269],"slot_index":3,"shape":3,"label":"CFG"},{"name":"SAMPLER","type":"COMBO","links":[4270],"slot_index":4,"shape":3,"label":"SAMPLER"},{"name":"SCHEDULER","type":"COMBO","links":[4271],"slot_index":5,"shape":3,"label":"SCHEDULER"}],"properties":{"Node name for S&R":"workflow/Ksampler Config"},"widgets_values":[6,24,3,"lcm","sgm_uniform"],"color":"#232","bgcolor":"#353"},{"id":95,"type":"Anything Everywhere?","pos":[1724,120],"size":{"0":212,"1":128},"flags":{"collapsed":true},"order":91,"mode":2,"inputs":[{"name":"COMBO","type":"*","link":4279,"label":"COMBO"}],"title":"scheduler","properties":{"Node name for S&R":"Anything Everywhere?","group_restricted":false,"color_restricted":false},"widgets_values":[".*","scheduler",".*"],"color":"#364736","bgcolor":"#223322"},{"id":96,"type":"Anything Everywhere?","pos":[1724,76],"size":{"0":212,"1":128},"flags":{"collapsed":true},"order":90,"mode":2,"inputs":[{"name":"COMBO","type":"*","link":4278,"label":"COMBO"}],"title":"sampler","properties":{"Node name for S&R":"Anything Everywhere?","group_restricted":false,"color_restricted":false},"widgets_values":[".*","sampler",".*"],"color":"#364736","bgcolor":"#223322"},{"id":97,"type":"Anything Everywhere?","pos":[1720,36],"size":{"0":212,"1":128},"flags":{"collapsed":true},"order":89,"mode":2,"inputs":[{"name":"FLOAT","type":"*","link":4277,"label":"FLOAT","color_on":""}],"title":"cfg","properties":{"Node name for S&R":"Anything Everywhere?","group_restricted":false,"color_restricted":false},"widgets_values":[".*","cfg",".*"],"color":"#364736","bgcolor":"#223322"},{"id":98,"type":"Anything Everywhere?","pos":[1720,-4],"size":{"0":212,"1":128},"flags":{"collapsed":true},"order":88,"mode":2,"inputs":[{"name":"INT","type":"*","link":4276,"label":"INT","color_on":"#29699C"}],"title":"steps","properties":{"Node name for S&R":"Anything Everywhere?","group_restricted":false,"color_restricted":false},"widgets_values":[".*","steps",".*"],"color":"#364736","bgcolor":"#223322"},{"id":99,"type":"LoraLoader","pos":[1212,-104],"size":{"0":296,"1":128},"flags":{},"order":68,"mode":2,"inputs":[{"name":"model","type":"MODEL","link":4254,"label":"model"},{"name":"clip","type":"CLIP","link":4255,"label":"clip"}],"outputs":[{"name":"MODEL","type":"MODEL","links":[4250],"slot_index":0,"shape":3,"label":"MODEL"},{"name":"CLIP","type":"CLIP","links":[4251],"slot_index":1,"shape":3,"label":"CLIP"}],"title":"Detail LoRA","properties":{"Node name for S&R":"LoraLoader"},"widgets_values":["add_detail.safetensors",0.8,0.8],"color":"#404440","bgcolor":"#2c302c"},{"id":100,"type":"Anything Everywhere","pos":[1720,-84],"size":{"0":212,"1":76},"flags":{"collapsed":true},"order":86,"mode":2,"inputs":[{"name":"MODEL","type":"*","link":4248,"color_on":"#B39DDB","label":"MODEL"}],"title":"model","properties":{"Node name for S&R":"Anything Everywhere","group_restricted":0,"color_restricted":0},"widgets_values":[],"color":"#364736","bgcolor":"#223322"},{"id":101,"type":"Anything Everywhere","pos":[1720,-44],"size":{"0":212,"1":76},"flags":{"collapsed":true},"order":87,"mode":2,"inputs":[{"name":"CLIP","type":"*","link":4249,"color_on":"#FFD500","label":"CLIP"}],"title":"clip","properties":{"Node name for S&R":"Anything Everywhere","group_restricted":0,"color_restricted":0},"widgets_values":[],"color":"#364736","bgcolor":"#223322"},{"id":102,"type":"workflow/Ksampler Config","pos":[1532,-104],"size":{"0":212,"1":232},"flags":{},"order":78,"mode":2,"inputs":[{"name":"model","type":"MODEL","link":4250,"label":"model"},{"name":"clip","type":"CLIP","link":4251,"label":"clip"}],"outputs":[{"name":"MODEL","type":"MODEL","links":[4248],"shape":3,"label":"MODEL"},{"name":"CLIP","type":"CLIP","links":[4249],"shape":3,"label":"CLIP"},{"name":"STEPS","type":"INT","links":[4276],"slot_index":2,"shape":3,"label":"STEPS"},{"name":"CFG","type":"FLOAT","links":[4277],"slot_index":3,"shape":3,"label":"CFG"},{"name":"SAMPLER","type":"COMBO","links":[4278],"slot_index":4,"shape":3,"label":"SAMPLER"},{"name":"SCHEDULER","type":"COMBO","links":[4279],"slot_index":5,"shape":3,"label":"SCHEDULER"}],"properties":{"Node name for S&R":"workflow/Ksampler Config"},"widgets_values":[12,24,3,"dpmpp_2m","karras"],"color":"#232","bgcolor":"#353"},{"id":103,"type":"Anything Everywhere?","pos":[2408,120],"size":{"0":212,"1":128},"flags":{"collapsed":true},"order":97,"mode":2,"inputs":[{"name":"COMBO","type":"*","link":4275,"label":"COMBO"}],"title":"scheduler","properties":{"Node name for S&R":"Anything Everywhere?","group_restricted":false,"color_restricted":false},"widgets_values":[".*","scheduler",".*"],"color":"#364736","bgcolor":"#223322"},{"id":104,"type":"Anything Everywhere?","pos":[2408,76],"size":{"0":212,"1":128},"flags":{"collapsed":true},"order":96,"mode":2,"inputs":[{"name":"COMBO","type":"*","link":4274,"label":"COMBO"}],"title":"sampler","properties":{"Node name for S&R":"Anything Everywhere?","group_restricted":false,"color_restricted":false},"widgets_values":[".*","sampler",".*"],"color":"#364736","bgcolor":"#223322"},{"id":105,"type":"Anything Everywhere?","pos":[2404,36],"size":{"0":212,"1":128},"flags":{"collapsed":true},"order":95,"mode":2,"inputs":[{"name":"FLOAT","type":"*","link":4273,"label":"FLOAT","color_on":""}],"title":"cfg","properties":{"Node name for S&R":"Anything Everywhere?","group_restricted":false,"color_restricted":false},"widgets_values":[".*","cfg",".*"],"color":"#364736","bgcolor":"#223322"},{"id":106,"type":"Anything Everywhere?","pos":[2404,-4],"size":{"0":212,"1":128},"flags":{"collapsed":true},"order":94,"mode":2,"inputs":[{"name":"INT","type":"*","link":4272,"label":"INT","color_on":"#29699C"}],"title":"steps","properties":{"Node name for S&R":"Anything Everywhere?","group_restricted":false,"color_restricted":false},"widgets_values":[".*","steps",".*"],"color":"#364736","bgcolor":"#223322"},{"id":107,"type":"LoraLoader","pos":[1896,-104],"size":{"0":296,"1":128},"flags":{},"order":69,"mode":2,"inputs":[{"name":"model","type":"MODEL","link":4256,"label":"model"},{"name":"clip","type":"CLIP","link":4257,"label":"clip"}],"outputs":[{"name":"MODEL","type":"MODEL","links":[4260],"slot_index":0,"shape":3,"label":"MODEL"},{"name":"CLIP","type":"CLIP","links":[4261],"slot_index":1,"shape":3,"label":"CLIP"}],"title":"Detail LoRA","properties":{"Node name for S&R":"LoraLoader"},"widgets_values":["add_detail.safetensors",0.8,0.8],"color":"#404440","bgcolor":"#2c302c"},{"id":108,"type":"Anything Everywhere","pos":[2404,-84],"size":{"0":212,"1":76},"flags":{"collapsed":true},"order":92,"mode":2,"inputs":[{"name":"MODEL","type":"*","link":4258,"color_on":"#B39DDB","label":"MODEL"}],"title":"model","properties":{"Node name for S&R":"Anything Everywhere","group_restricted":0,"color_restricted":0},"widgets_values":[],"color":"#364736","bgcolor":"#223322"},{"id":109,"type":"Anything Everywhere","pos":[2404,-44],"size":{"0":212,"1":76},"flags":{"collapsed":true},"order":93,"mode":2,"inputs":[{"name":"CLIP","type":"*","link":4259,"color_on":"#FFD500","label":"CLIP"}],"title":"clip","properties":{"Node name for S&R":"Anything Everywhere","group_restricted":0,"color_restricted":0},"widgets_values":[],"color":"#364736","bgcolor":"#223322"},{"id":110,"type":"workflow/Ksampler Config","pos":[2216,-104],"size":{"0":212,"1":232},"flags":{},"order":79,"mode":2,"inputs":[{"name":"model","type":"MODEL","link":4260,"label":"model"},{"name":"clip","type":"CLIP","link":4261,"label":"clip"}],"outputs":[{"name":"MODEL","type":"MODEL","links":[4258],"shape":3,"label":"MODEL"},{"name":"CLIP","type":"CLIP","links":[4259],"shape":3,"label":"CLIP"},{"name":"STEPS","type":"INT","links":[4272],"slot_index":2,"shape":3,"label":"STEPS"},{"name":"CFG","type":"FLOAT","links":[4273],"slot_index":3,"shape":3,"label":"CFG"},{"name":"SAMPLER","type":"COMBO","links":[4274],"slot_index":4,"shape":3,"label":"SAMPLER"},{"name":"SCHEDULER","type":"COMBO","links":[4275],"slot_index":5,"shape":3,"label":"SCHEDULER"}],"properties":{"Node name for S&R":"workflow/Ksampler Config"},"widgets_values":[24,24,3,"dpmpp_2m","karras"],"color":"#232","bgcolor":"#353"},{"id":111,"type":"Note Plus (mtb)","pos":{"0":-952,"1":528,"2":0,"3":0,"4":0,"5":0,"6":0,"7":0,"8":0,"9":0},"size":[656,128],"flags":{},"order":20,"mode":2,"inputs":[],"outputs":[],"properties":{},"widgets_values":["<div class=\"startPage\">\n  <div class=\"hoverContainer\">\n    <a href=\"https://openart.ai/workflows/lreWarJbqiYPcDXnD8hh\">\n      <span class=\"size-smallButton style-input\">🗃️ Required Files</span>\n    </a>\n    <a href=\"https://github.com/NimaNzrii/comfyui-photoshop/issues/new\">\n      <span class=\"size-smallButton style-input\">🪲 Report Bug</span>\n    </a>\n    <a href=\"https://buymeacoffee.com/nimanzri\">\n      <span class=\"size-smallButton style-input\">☕ Buy Me a Coffee</span>\n    </a>\n  </div>\n</div>\n","markdown","* {\n    font-family: Arial;\n  }\n\n\n  .startPage {\n    position: absolute;\n    width:auto;\n    z-index: 0;\n    transition: transform 0.3s ease;\n  }\n\n  .startPage:hover {\n    transform: translateY(-1%);\n  }\n\n  .hoverContainer {\n    background: black;\n    border-radius: 27px;\n    padding: 18px;\ndisplay: flex;\nflex-direction: row;\n    margin: 12px auto;\n    position: relative;\n  }\n\n  .header {\n    padding-bottom: 12px;\n    margin-bottom: 12px;\n    border-bottom: 1px solid #3e3e3e;\n    width: 100%;\n    height: 36px;\n    display: flex;\n    align-items: center;\n    justify-content: space-between;\n  }\n\n  .header_discrip {\n    font-size: 21px;\n    font-weight: 200;\n    color: #6f6f6f;\n  }\n\n  .size-smallButton {\n    font-size: 21px;\n    border-radius: 12px;\n    height: 48px;\n    min-width: 48px;\n    display: flex;\n    align-items: center;\n    justify-content: center;\n    width: 100%;\n    cursor: pointer;\n  }\n\n  .style-input {\n    background: #2a2a2b;\n    padding: 12px;\n    transition: background 0.3s;\n  }\n\n  .style-input:hover {\n    background: #3b3b3c;\n  }\na:not(:first-child) {\n      margin-left:8px;}\n  a {\n    color: #b6b6b7;\n  }\n\n  a:hover,\n  a:hover .header_discrip {\n    color: #dddddd !important;\n  }","one_dark"],"color":"#3a3a3a","bgcolor":"#262626","shape":1}],"links":[[516,4,0,5,2,"CONTROL_NET"],[517,6,0,5,3,"IMAGE"],[520,7,0,5,7,"CONTROL_NET_WEIGHTS"],[1254,7,1,5,5,"TIMESTEP_KEYFRAME"],[1506,1,0,11,3,"LATENT"],[1523,8,0,12,1,"CONDITIONING"],[1524,8,1,12,2,"CONDITIONING"],[1554,16,0,17,2,"CONTROL_NET"],[1556,17,0,18,1,"CONDITIONING"],[1557,17,1,18,2,"CONDITIONING"],[2141,15,0,19,0,"LATENT"],[2144,11,0,20,0,"LATENT"],[2146,13,0,21,0,"LATENT"],[2148,12,0,22,0,"LATENT"],[2150,18,0,23,0,"LATENT"],[2152,14,0,24,0,"LATENT"],[2196,25,0,17,3,"IMAGE"],[2654,3,0,31,0,"MODEL"],[2655,31,0,13,0,"MODEL"],[2732,32,0,13,1,"CONDITIONING"],[2733,32,1,13,2,"CONDITIONING"],[2736,32,2,13,3,"LATENT"],[2908,10,0,11,2,"CONDITIONING"],[2909,9,0,11,1,"CONDITIONING"],[2910,34,0,17,0,"CONDITIONING"],[2911,35,0,17,1,"CONDITIONING"],[2912,33,0,18,3,"LATENT"],[2913,38,0,12,3,"LATENT"],[2914,36,0,8,0,"CONDITIONING"],[2915,37,0,8,1,"CONDITIONING"],[2916,39,0,32,0,"CONDITIONING"],[2917,40,0,32,1,"CONDITIONING"],[2918,41,0,5,0,"CONDITIONING"],[2919,42,0,5,1,"CONDITIONING"],[2921,46,0,15,3,"LATENT"],[2922,45,0,15,2,"CONDITIONING"],[2923,44,0,15,1,"CONDITIONING"],[2926,3,1,40,0,"CLIP"],[2927,3,1,39,0,"CLIP"],[2930,2,0,8,2,"CONTROL_NET"],[2961,26,2,49,0,"VAE"],[3143,51,0,50,0,"MODEL"],[3144,51,1,50,1,"CLIP"],[3177,53,0,52,0,"UPSCALE_MODEL"],[3243,54,0,8,3,"IMAGE"],[3682,5,0,14,1,"CONDITIONING"],[3683,5,1,14,2,"CONDITIONING"],[3684,43,0,14,3,"LATENT"],[3715,55,0,43,2,"MASK"],[3716,55,0,6,1,"MASK"],[3941,5,2,14,0,"MODEL"],[4072,57,4,9,1,"STRING"],[4073,57,5,10,1,"STRING"],[4074,57,0,1,0,"IMAGE"],[4075,57,2,11,7,"FLOAT"],[4076,57,3,11,9,"INT"],[4088,58,4,34,1,"STRING"],[4089,58,5,35,1,"STRING"],[4090,58,0,33,0,"IMAGE"],[4091,58,2,18,9,"FLOAT"],[4092,59,6,38,0,"INT"],[4093,59,7,38,1,"INT"],[4094,59,4,36,1,"STRING"],[4095,59,5,37,1,"STRING"],[4097,60,1,8,4,"FLOAT"],[4098,59,2,60,0,"INT,FLOAT"],[4099,59,0,54,0,"IMAGE"],[4100,54,0,61,0,"IMAGE"],[4104,62,0,32,3,"IMAGE"],[4105,62,1,32,4,"MASK"],[4107,62,4,39,1,"STRING"],[4108,62,5,40,1,"STRING"],[4109,3,2,32,2,"VAE"],[4110,63,4,41,1,"STRING"],[4111,63,5,42,1,"STRING"],[4112,62,3,13,4,"INT"],[4113,59,3,12,4,"INT"],[4114,58,3,18,4,"INT"],[4115,63,0,6,0,"IMAGE"],[4116,63,1,55,0,"MASK"],[4117,63,3,14,4,"INT"],[4121,64,6,46,0,"INT"],[4122,64,7,46,1,"INT"],[4123,64,4,44,1,"STRING"],[4124,64,5,45,1,"STRING"],[4126,65,0,52,1,"IMAGE"],[4128,63,0,43,0,"IMAGE"],[4129,64,3,15,4,"INT"],[4130,58,0,25,0,"IMAGE"],[4131,25,0,66,0,"IMAGE"],[4137,20,0,70,0,"IMAGE"],[4140,19,0,71,0,"IMAGE"],[4141,52,0,72,0,"IMAGE"],[4142,23,0,73,0,"IMAGE"],[4143,22,0,74,0,"IMAGE"],[4144,24,0,75,0,"IMAGE"],[4145,21,0,76,0,"IMAGE"],[4163,77,0,51,0,"MODEL"],[4164,78,0,51,1,"CLIP"],[4169,79,0,77,0,"*"],[4170,26,0,79,0,"*"],[4171,26,1,80,0,"*"],[4173,80,0,78,0,"*"],[4178,80,0,81,0,"*"],[4234,50,0,85,0,"MODEL"],[4235,50,1,85,1,"CLIP"],[4236,91,0,90,0,"MODEL"],[4237,91,1,90,1,"CLIP"],[4238,77,0,91,0,"MODEL"],[4239,78,0,91,1,"CLIP"],[4240,94,0,92,0,"MODEL"],[4241,94,1,93,0,"CLIP"],[4242,90,0,94,0,"MODEL"],[4243,90,1,94,1,"CLIP"],[4248,102,0,100,0,"MODEL"],[4249,102,1,101,0,"CLIP"],[4250,99,0,102,0,"MODEL"],[4251,99,1,102,1,"CLIP"],[4253,79,0,82,0,"*"],[4254,82,0,99,0,"MODEL"],[4255,81,0,99,1,"CLIP"],[4256,82,0,107,0,"MODEL"],[4257,81,0,107,1,"CLIP"],[4258,110,0,108,0,"MODEL"],[4259,110,1,109,0,"CLIP"],[4260,107,0,110,0,"MODEL"],[4261,107,1,110,1,"CLIP"],[4262,85,2,30,0,"INT"],[4263,85,1,84,0,"CLIP"],[4264,85,0,83,0,"MODEL"],[4265,85,3,29,0,"FLOAT"],[4266,85,4,28,0,"COMBO"],[4267,85,5,27,0,"COMBO"],[4268,94,2,89,0,"INT"],[4269,94,3,88,0,"FLOAT"],[4270,94,4,87,0,"COMBO"],[4271,94,5,86,0,"COMBO"],[4272,110,2,106,0,"INT"],[4273,110,3,105,0,"FLOAT"],[4274,110,4,104,0,"COMBO"],[4275,110,5,103,0,"COMBO"],[4276,102,2,98,0,"INT"],[4277,102,3,97,0,"FLOAT"],[4278,102,4,96,0,"COMBO"],[4279,102,5,95,0,"COMBO"],[4301,26,2,1,1,"VAE"],[4302,94,0,9,0,"CLIP"],[4303,94,0,10,0,"CLIP"],[4304,94,0,11,0,"MODEL"],[4305,94,0,11,4,"INT"],[4306,94,2,11,5,"FLOAT"],[4307,94,3,11,6,"COMBO"],[4308,94,4,11,8,"COMBO"],[4309,26,2,20,1,"VAE"]],"groups":[{"title":"Txt 2 Img","bounding":[2404,508,1159,394],"color":"#3f789e","font_size":60,"locked":false},{"title":"img 2 img","bounding":[1180,508,1179,388],"color":"#3f789e","font_size":60,"locked":false},{"title":"img 2 img⁽ˢᶜʳⁱᵇᵇˡᵉ ᶜⁿ⁾","bounding":[1180,1368,1975,398],"color":"#3f789e","font_size":60,"locked":false},{"title":"in-Paint","bounding":[1178,2292,1376,418],"color":"#3f789e","font_size":60,"locked":false},{"title":"Out Paint","bounding":[1182,1798,1732,456],"color":"#3f789e","font_size":64,"locked":false},{"title":"LCM 6ˢᵗᵉᵖ","bounding":[1888,-696,644,428],"color":"#8A8","font_size":60,"locked":false},{"title":"24ˢᵗᵉᵖ","bounding":[1888,-228,644,366],"color":"#8A8","font_size":60,"locked":false},{"title":"img 2 img⁽ˡⁱⁿᵉ ᶜⁿ⁾","bounding":[1180,936,1947,394],"color":"#3f789e","font_size":60,"locked":false},{"title":"12ˢᵗᵉᵖ","bounding":[1200,-228,644,366],"color":"#8A8","font_size":60,"locked":false},{"title":"⚡LCM 4ˢᵗᵉᵖ","bounding":[1200,-696,644,428],"color":"#8A8","font_size":60,"locked":false},{"title":"Simple Fast Upscale","bounding":[3600,508,803,390],"color":"#3f789e","font_size":60,"locked":false}],"config":{},"extra":{"ds":{"scale":0.2100000000000017,"offset":[2317.784769993924,806.4582013691239]},"groupNodes":{"Ksampler Config":{"nodes":[{"type":"🔹modelPass","pos":[1900,-624],"size":{"0":210,"1":26},"flags":{},"order":106,"mode":0,"inputs":[{"name":"model","type":"MODEL","link":null}],"outputs":[{"name":"model","type":"MODEL","links":[],"shape":3,"slot_index":0}],"properties":{"Node name for S&R":"🔹modelPass"},"index":0},{"type":"🔹ClipPass","pos":[1896,-548],"size":{"0":210,"1":26},"flags":{},"order":108,"mode":0,"inputs":[{"name":"clip","type":"CLIP","link":null}],"outputs":[{"name":"clip","type":"CLIP","links":[],"shape":3,"slot_index":0}],"properties":{"Node name for S&R":"🔹ClipPass"},"index":1},{"type":"KSampler Config (rgthree)","pos":[1916,-428],"size":{"0":315,"1":234},"flags":{},"order":30,"mode":0,"outputs":[{"name":"STEPS","type":"INT","links":null,"shape":3},{"name":"REFINER_STEP","type":"INT","links":null,"shape":3},{"name":"CFG","type":"FLOAT","links":null,"shape":3},{"name":"SAMPLER","type":"COMBO","links":null,"shape":3},{"name":"SCHEDULER","type":"COMBO","links":null,"shape":3}],"properties":{"Node name for S&R":"KSampler Config (rgthree)"},"widgets_values":[30,24,8,"euler","normal"],"index":2}],"links":[[null,0,0,0,1391,"MODEL"],[null,1,1,0,1391,"CLIP"]],"external":[[{"type":"🔹modelPass","pos":[1900,-624],"size":{"0":210,"1":26},"flags":{},"order":106,"mode":0,"inputs":[{"name":"model","type":"MODEL","link":null}],"outputs":[{"name":"model","type":"MODEL","links":[],"shape":3,"slot_index":0}],"properties":{"Node name for S&R":"🔹modelPass"},"index":0},0,"MODEL"],[{"type":"🔹ClipPass","pos":[1896,-548],"size":{"0":210,"1":26},"flags":{},"order":108,"mode":0,"inputs":[{"name":"clip","type":"CLIP","link":null}],"outputs":[{"name":"clip","type":"CLIP","links":[],"shape":3,"slot_index":0}],"properties":{"Node name for S&R":"🔹ClipPass"},"index":1},0,"CLIP"]],"config":{"0":{"output":{"0":{"name":"MODEL"}}},"1":{"output":{"0":{"name":"CLIP"}}},"2":{"output":{"0":{"name":"STEPS"},"1":{"visible":false}},"input":{"refiner_step":{"visible":false},"steps_total":{"name":"steps"}}}}}},"0246.VERSION":[0,0,4]},"version":0.4}